Sidebend_detection/Sidebend_detection.py
Sidebend_detection/__init__.py
Sidebend_detection-0.2.dist-info/METADATA
Sidebend_detection-0.2.dist-info/WHEEL
Sidebend_detection-0.2.dist-info/top_level.txt
Sidebend_detection-0.2.dist-info/RECORD
