Metadata-Version: 2.1
Name: Sidebend-detection
Version: 0.2
Summary: Sidebend detection
Home-page: http://github.com/1104934392/Sidebend_detection
Author: 1104934392
Author-email: 1104934392@qq.com
License: MIT
Platform: UNKNOWN
Requires-Dist: numpy
